[
  {
    "icon": "Blog",
    "name": "博客",
    "link": "https://yuai.cloud/"
  },
  {
    "icon": "Book",
    "name": "AI",
    "link": "https://chat.yuai.cloud/"
  },
  {
    "icon": "Compass",
    "name": "导航",
    "link": "https://go.itab.link/"
  },
  {
    "icon": "Cloud",
    "name": "网盘",
    "link": "https://eva.yuai.fun/admin"
  },
  {
    "icon": "CompactDisc",
    "name": "音乐",
    "link": "https://music.yuai.cloud/"
  },
  {
    "icon": "Fire",
    "name": "流量",
    "link": "https://umami.yuai.cloud/"
  },
  {
    "icon": "LaptopCode",
    "name": "站点",
    "link": "https://status.yuai.cloud/"
  }
]
