[
  {
    "icon": "Blog",
    "name": "博客",
    "link": "https://yuai.cloud/"
  },
  {
    "icon": "Book",
    "name": "导航页",
    "link": "https://web.yuai.cloud/"
  },
  {
    "icon": "Cloud",
    "name": "网盘",
    "link": "https://eva.yuai.cloud/"
  },
  {
    "icon": "Compass",
    "name": "首页",
    "link": "https://home.yuai.cloud/"
  },
  {
    "icon": "CompactDisc",
    "name": "音乐",
    "link": "https://music.yuai.cloud/"
  },
  {
    "icon": "LaptopCode",
    "name": "站点监测",
    "link": "https://status.yuai.cloud/"
  },
  {
    "icon": "Fire",
    "name": "流量监控",
    "link": "https://umami.yuai.cloud/"
  }
]
